data_manipulation/__init__.py
data_manipulation/_version.py
data_manipulation/base.py
data_manipulation/beautifulsoup_.py
data_manipulation/django_.py
data_manipulation/flask_.py
data_manipulation/geopandas_.py
data_manipulation/mysql_connector_python_.py
data_manipulation/pandas_.py
data_manipulation/psycopg2_.py
data_manipulation/pyspark_.py
data_manipulation-0.33.dist-info/LICENSE
data_manipulation-0.33.dist-info/METADATA
data_manipulation-0.33.dist-info/WHEEL
data_manipulation-0.33.dist-info/top_level.txt
data_manipulation-0.33.dist-info/RECORD
