Metadata-Version: 2.1
Name: data-manipulation
Version: 0.33
Summary: Powerful data manipulation
Home-page: https://github.com/shawnngtq/data-manipulation
Author: Shawn Ng
Author-email: shawn.coding.acc@gmail.com
License: BSD-3
Platform: any
Classifier: Development Status :: 3 - Alpha
Classifier: Environment :: Console
Classifier: Operating System :: OS Independent
Classifier: Intended Audience :: Science/Research
Classifier: Programming Language :: Python
Classifier: Programming Language :: Python :: 3
Classifier: Programming Language :: Python :: 3.6
Classifier: Programming Language :: Python :: 3.7
Classifier: Programming Language :: Python :: 3.8
Classifier: Programming Language :: Python :: 3.9
Classifier: Programming Language :: Cython
Classifier: Topic :: Scientific/Engineering
License-File: LICENSE
Requires-Dist: beautifulsoup4
Requires-Dist: django
Requires-Dist: lxml
Requires-Dist: matplotlib
Requires-Dist: mysql-connector-python
Requires-Dist: pandas
Requires-Dist: psycopg2
Requires-Dist: pyspark
Requires-Dist: seaborn
Requires-Dist: tqdm
Requires-Dist: xlsxwriter
